README.rst
setup.cfg
setup.py
pcapng/__init__.py
pcapng/block.py
pcapng/block_test.py
pcapng/codec.py
pcapng/const.py
pcapng/linktype.py
pcapng/mrt.py
pcapng/mrt_test.py
pcapng/option.py
pcapng/option_test.py
pcapng/pen.py
pcapng/tlv.py
pcapng/tlv_test.py
pcapng/util.py
pcapng/util_test.py
pcapng3.egg-info/PKG-INFO
pcapng3.egg-info/SOURCES.txt
pcapng3.egg-info/dependency_links.txt
pcapng3.egg-info/requires.txt
pcapng3.egg-info/top_level.txt